{
  "policy_id": "https://www.cms.gov/medicare-coverage-database/view/article.aspx?articleId=57765",
  "version": "2025-10-01",
  "lob": "commercial",
  "codes": [
    "27487"
  ],
  "requires_pa": true,
  "inclusion": [
    {
      "gte": [
        "age_years",
        18
      ]
    },
    {
      "lte": [
        "age_years",
        80
      ]
    },
    {
      "in": [
        "primary_icd10",
        [
          57002,
          98461,
          35823,
          60385,
          59044,
          23965,
          23043,
          15508,
          17428,
          79534,
          98629,
          25588,
          39104,
          76912,
          34418,
          10583,
          98499,
          2576,
          59321,
          34559,
          70962,
          42398,
          30198,
          669,
          89346,
          47814,
          66714,
          96480,
          32758,
          57429,
          64004,
          23544,
          88289,
          89686,
          5146,
          11419,
          46956,
          61791,
          52859,
          63510,
          23343,
          14596,
          14530,
          93913,
          79965,
          49047,
          33632,
          30573,
          74553,
          9779,
          57195,
          90034,
          45171,
          31447,
          74600,
          82096,
          94117,
          80558,
          57238,
          18701,
          29229,
          99778,
          77543,
          30490,
          24772,
          7766,
          37013,
          4846,
          41478,
          72129,
          73430,
          12696,
          64457,
          15124,
          80649,
          9654,
          48161,
          92448,
          35828,
          62610,
          53001,
          2337,
          5609,
          8730,
          116,
          89005,
          79918,
          7474,
          37208,
          82941,
          49559,
          79350,
          94144,
          72640,
          43070,
          2453,
          59765,
          2757,
          99398,
          8964,
          76828,
          81869,
          73388,
          51185,
          1654,
          24323,
          72946,
          97290,
          99720,
          94740,
          51443,
          8438,
          99540,
          97576,
          31022,
          36531,
          18050,
          45716,
          99284,
          21945,
          24383,
          96873,
          70979,
          5816,
          13252,
          27088,
          28110,
          34484,
          8390,
          82109,
          12082,
          28724,
          17098,
          10737,
          67889,
          39841,
          90769,
          98964,
          31035,
          92696,
          57261,
          67124,
          34659,
          93554,
          45339,
          1084,
          56563,
          85364,
          39222,
          10506,
          73299,
          74851,
          98180,
          18343,
          18919,
          367,
          53677,
          19718,
          22505,
          41900,
          45421,
          85265,
          13680,
          47699,
          91353,
          70450,
          405,
          81875,
          76043,
          28447,
          23932,
          84816,
          98191,
          39741,
          21827,
          62585,
          10176,
          6172,
          40879,
          13529,
          31877,
          41355,
          94970,
          21408,
          78851,
          7319,
          31365,
          94586,
          73034,
          88470,
          46218,
          10068,
          36076,
          91551,
          7099,
          69405,
          44530,
          85007,
          33647,
          19734,
          61717,
          30602,
          39194,
          48775,
          47233,
          19683,
          73802,
          70923,
          62873,
          14372,
          37583,
          6328,
          91582,
          45304
        ]
      ]
    }
  ],
  "exclusion": [],
  "admin_rules": {
    "max_units_per_day": 1,
    "pos_allowed": [
      22,
      24
    ]
  }
}